yahoowizard/__init__.py
yahoowizard/draft_logic.py
yahoowizard/process_and_map_projections.py
yahoowizard/update_probabilities.py
yahoowizard/yahoo_draft.py
yahoo_draft_wizard-0.0.8.dist-info/LICENSE
yahoo_draft_wizard-0.0.8.dist-info/METADATA
yahoo_draft_wizard-0.0.8.dist-info/WHEEL
yahoo_draft_wizard-0.0.8.dist-info/top_level.txt
yahoo_draft_wizard-0.0.8.dist-info/RECORD
