Metadata-Version: 2.1
Name: yahoo-draft-wizard
Version: 0.0.8
Summary: Dynamically recommends picks for your yahoo fantasy football draft
Home-page: https://github.com/jwaggie14/yahoo-draft-wizard
Author: James Whiting
Author-email: jlwhiting@outlook.com
License: UNKNOWN
Platform: UNKNOWN
Classifier: Programming Language :: Python :: 3
Classifier: License :: OSI Approved :: GNU General Public License v3 (GPLv3)
Classifier: Operating System :: OS Independent
Requires-Python: >=3.7
Requires-Dist: numpy
Requires-Dist: pandas
Requires-Dist: yahoo-oauth
